MANIFEST.in
setup.cfg
setup.py
Flask_Swagger_Codegen.egg-info/PKG-INFO
Flask_Swagger_Codegen.egg-info/SOURCES.txt
Flask_Swagger_Codegen.egg-info/dependency_links.txt
Flask_Swagger_Codegen.egg-info/entry_points.txt
Flask_Swagger_Codegen.egg-info/requires.txt
Flask_Swagger_Codegen.egg-info/top_level.txt
flask_swagger_codegen/__init__.py
flask_swagger_codegen/__init__.pyc
flask_swagger_codegen/__main__.py
flask_swagger_codegen/__main__.pyc
flask_swagger_codegen/generator.py
flask_swagger_codegen/generator.pyc
flask_swagger_codegen/model.py
flask_swagger_codegen/model.pyc
flask_swagger_codegen/parser.py
flask_swagger_codegen/parser.pyc
flask_swagger_codegen/resolver.py
flask_swagger_codegen/resolver.pyc
flask_swagger_codegen/writer.py
flask_swagger_codegen/writer.pyc
flask_swagger_codegen/templates/_do_not_change.tpl
flask_swagger_codegen/templates/api.tpl
flask_swagger_codegen/templates/app.tpl
flask_swagger_codegen/templates/blueprint.tpl
flask_swagger_codegen/templates/filters.tpl
flask_swagger_codegen/templates/init.tpl
flask_swagger_codegen/templates/requirements.tpl
flask_swagger_codegen/templates/routes.tpl
flask_swagger_codegen/templates/schemas.tpl
flask_swagger_codegen/templates/validators.tpl
flask_swagger_codegen/templates/view_test.tpl
flask_swagger_codegen/templates/views.tpl