Metadata-Version: 1.1
Name: Flask-Swagger-Codegen
Version: 0.0.6
Summary: Generate Flask code from Swagger docs.
Home-page: http://github.com/rejown/flask-swagger-codegen
Author: Rejown
Author-email: rejown@gmail.com
License: UNKNOWN
Platform: UNKNOWN
Classifier: Development Status :: 3 - Alpha
Classifier: License :: OSI Approved :: MIT License
Classifier: Programming Language :: Python :: 2.7
